{
  "hash": "1cc01170",
  "browserHash": "b401e16b",
  "optimized": {
    "vue": {
      "src": "../../node_modules/vue/dist/vue.runtime.esm-bundler.js",
      "file": "vue.js",
      "fileHash": "9e214288",
      "needsInterop": false
    },
    "vue-router": {
      "src": "../../node_modules/vue-router/dist/vue-router.mjs",
      "file": "vue-router.js",
      "fileHash": "2df16eef",
      "needsInterop": false
    },
    "element-plus": {
      "src": "../../node_modules/element-plus/es/index.mjs",
      "file": "element-plus.js",
      "fileHash": "94bdc647",
      "needsInterop": false
    },
    "@vueuse/core": {
      "src": "../../node_modules/@vueuse/core/index.mjs",
      "file": "@vueuse_core.js",
      "fileHash": "f3e5c47c",
      "needsInterop": false
    },
    "@popperjs/core": {
      "src": "../../node_modules/@popperjs/core/dist/index.mjs",
      "file": "@popperjs_core.js",
      "fileHash": "9d4b5f75",
      "needsInterop": false
    },
    "d3-force": {
      "src": "../../node_modules/d3-force/src/index.js",
      "file": "d3-force.js",
      "fileHash": "0d4be2d7",
      "needsInterop": false
    },
    "semver": {
      "src": "../../node_modules/semver/index.js",
      "file": "semver.js",
      "fileHash": "8395ad0d",
      "needsInterop": true
    },
    "spark-md5": {
      "src": "../../node_modules/spark-md5/spark-md5.js",
      "file": "spark-md5.js",
      "fileHash": "59c961ca",
      "needsInterop": true
    }
  },
  "chunks": {
    "chunk-WW3H7SQG": {
      "file": "chunk-WW3H7SQG.js"
    },
    "chunk-TUTPZM3B": {
      "file": "chunk-TUTPZM3B.js"
    },
    "chunk-2QGY6IU7": {
      "file": "chunk-2QGY6IU7.js"
    },
    "chunk-TWLJ45QX": {
      "file": "chunk-TWLJ45QX.js"
    }
  }
}